deepcolor/__init__.py
deepcolor/commons.py
deepcolor/dataset.py
deepcolor/exp.py
deepcolor/funcs.py
deepcolor/modules.py
deepcolor/workflow.py
deepcolor-0.0.6.dist-info/LICENSE
deepcolor-0.0.6.dist-info/METADATA
deepcolor-0.0.6.dist-info/WHEEL
deepcolor-0.0.6.dist-info/top_level.txt
deepcolor-0.0.6.dist-info/RECORD
