Metadata-Version: 2.1
Name: deepcolor
Version: 0.0.6
Summary: Analyze colocalization patterns between single cell gene expression profiles.
Home-page: https://github.com/kojikoji/deepcolor
Author: Kojima Yasuhiro
Author-email: tiisaishima@gmail.com
Project-URL: Bug Tracker, https://github.com/kojikoji/deepcolor/issues
Classifier: Programming Language :: Python :: 3
Classifier: License :: OSI Approved :: MIT License
Classifier: Operating System :: OS Independent
Requires-Python: >=3.7
License-File: LICENSE
Requires-Dist: scanpy >=1.7.2
Requires-Dist: torch >=1.7.0
Requires-Dist: plotly >=5.3.1
Requires-Dist: matplotlib <=3.6.3
Requires-Dist: plotnine >=0.8.0
